setup.cfg
setup.py
django_trampoline.egg-info/PKG-INFO
django_trampoline.egg-info/SOURCES.txt
django_trampoline.egg-info/dependency_links.txt
django_trampoline.egg-info/entry_points.txt
django_trampoline.egg-info/not-zip-safe
django_trampoline.egg-info/requires.txt
django_trampoline.egg-info/top_level.txt
nose_plugins/__init__.py
nose_plugins/trampoline_setup.py
tests/__init__.py
tests/base.py
tests/celery_app.py
tests/doc_types.py
tests/models.py
tests/settings.py
tests/test_commands.py
tests/test_mixins.py
tests/test_paginator.py
tests/views.py
trampoline/__init__.py
trampoline/apps.py
trampoline/mixins.py
trampoline/models.py
trampoline/paginator.py
trampoline/tasks.py
trampoline/version.py
trampoline/views.py
trampoline/management/__init__.py
trampoline/management/base.py
trampoline/management/commands/__init__.py
trampoline/management/commands/es_create_alias.py
trampoline/management/commands/es_create_documents.py
trampoline/management/commands/es_create_index.py
trampoline/management/commands/es_delete_alias.py
trampoline/management/commands/es_delete_index.py