Metadata-Version: 1.1
Name: django-trampoline
Version: 1.0
Summary: No-frills Elasticsearch's wrapper for your Django project.
Home-page: https://github.com/laurentguilbert/django-trampoline
Author: Laurent Guilbert
Author-email: laurent@guilbert.me
License: MIT License
Keywords: django,elasticsearch
Platform: UNKNOWN
Classifier: Framework :: Django
Classifier: Environment :: Web Environment
Classifier: Programming Language :: Python
Classifier: Programming Language :: Python :: 3
Classifier: Intended Audience :: Developers
Classifier: Operating System :: OS Independent
Classifier: Topic :: Software Development :: Libraries :: Python Modules
